wagtailsurveys/__init__.py
wagtailsurveys/admin_urls.py
wagtailsurveys/apps.py
wagtailsurveys/forms.py
wagtailsurveys/models.py
wagtailsurveys/views.py
wagtailsurveys/wagtail_hooks.py
wagtailsurveys/locale/.gitkeep
wagtailsurveys/migrations/0001_initial.py
wagtailsurveys/migrations/__init__.py
wagtailsurveys/templates/wagtailsurveys/confirm_delete.html
wagtailsurveys/templates/wagtailsurveys/index.html
wagtailsurveys/templates/wagtailsurveys/index_submissions.html
wagtailsurveys/templates/wagtailsurveys/list_forms.html
wagtailsurveys/templates/wagtailsurveys/list_submissions.html
wagtailsurveys/templates/wagtailsurveys/results_forms.html
wagtailsurveys/tests/.gitignore
wagtailsurveys/tests/__init__.py
wagtailsurveys/tests/settings.py
wagtailsurveys/tests/test_forms.py
wagtailsurveys/tests/test_models.py
wagtailsurveys/tests/test_views.py
wagtailsurveys/tests/urls.py
wagtailsurveys/tests/utils.py
wagtailsurveys/tests/testapp/__init__.py
wagtailsurveys/tests/testapp/apps.py
wagtailsurveys/tests/testapp/models.py
wagtailsurveys/tests/testapp/fixtures/test.json
wagtailsurveys/tests/testapp/migrations/0001_initial.py
wagtailsurveys/tests/testapp/migrations/__init__.py
wagtailsurveys/tests/testapp/templates/wagtailsurveys_tests/base.html
wagtailsurveys/tests/testapp/templates/wagtailsurveys_tests/survey_page.html
wagtailsurveys/tests/testapp/templates/wagtailsurveys_tests/survey_page_landing.html
wagtailsurveys/tests/testapp/templates/wagtailsurveys_tests/survey_with_custom_submission_page.html
wagtailsurveys/tests/testapp/templates/wagtailsurveys_tests/survey_with_custom_submission_page_landing.html
wagtailsurveys-0.2.0.dist-info/LICENSE
wagtailsurveys-0.2.0.dist-info/METADATA
wagtailsurveys-0.2.0.dist-info/WHEEL
wagtailsurveys-0.2.0.dist-info/top_level.txt
wagtailsurveys-0.2.0.dist-info/RECORD
